AUTHORS
LICENSE
MANIFEST.in
README.md
pyproject.toml
src/opentaskpy/addons/o365/__init__.py
src/opentaskpy/addons/o365/remotehandlers/__init__.py
src/opentaskpy/addons/o365/remotehandlers/creds.py
src/opentaskpy/addons/o365/remotehandlers/sharepoint.py
src/opentaskpy/addons/o365/remotehandlers/schemas/transfer/sharepoint_destination.json
src/opentaskpy/addons/o365/remotehandlers/schemas/transfer/sharepoint_source.json
src/opentaskpy/addons/o365/remotehandlers/schemas/transfer/sharepoint_destination/protocol.json
src/opentaskpy/addons/o365/remotehandlers/schemas/transfer/sharepoint_destination/rename.json
src/opentaskpy/addons/o365/remotehandlers/schemas/transfer/sharepoint_source/fileWatch.json
src/opentaskpy/addons/o365/remotehandlers/schemas/transfer/sharepoint_source/postCopyAction.json
src/opentaskpy/addons/o365/remotehandlers/schemas/transfer/sharepoint_source/protocol.json
src/otf_addons_o365.egg-info/PKG-INFO
src/otf_addons_o365.egg-info/SOURCES.txt
src/otf_addons_o365.egg-info/dependency_links.txt
src/otf_addons_o365.egg-info/requires.txt
src/otf_addons_o365.egg-info/top_level.txt
tests/test_taskhandler_transfer_sharepoint.py