Metadata-Version: 2.4
Name: otf-addons-o365
Version: 25.34.0
Summary: Addons for opentaskpy, giving it the ability to push/pull via Sharepoint using the MS Graph API.
Author-email: Adam McDonagh <adam@elitemonkey.net>
License: GPLv3
Project-URL: Homepage, https://github.com/adammcdonagh/otf-addons-o365
Project-URL: Bug Tracker, https://github.com/adammcdonagh/otf-addons-o365/issues
Project-URL: Changelog, https://github.com/adammcdonagh/otf-addons-o365/blob/main/CHANGELOG.md
Keywords: automation,task,framework,o365,sharepoint,otf
Classifier: Programming Language :: Python :: 3
Classifier: License :: OSI Approved :: GNU General Public License v3 (GPLv3)
Classifier: Operating System :: POSIX
Requires-Python: >=3.11
License-File: LICENSE
License-File: AUTHORS
Requires-Dist: python-dateutil
Requires-Dist: requests
Requires-Dist: msal
Requires-Dist: opentaskpy>=v24.23.0
Provides-Extra: dev
Requires-Dist: pytest-shell; extra == "dev"
Requires-Dist: types-requests; extra == "dev"
Requires-Dist: types-python-dateutil; extra == "dev"
Requires-Dist: black>=24.1.1; extra == "dev"
Requires-Dist: isort; extra == "dev"
Requires-Dist: pytest; extra == "dev"
Requires-Dist: bumpver; extra == "dev"
Requires-Dist: pre-commit; extra == "dev"
Requires-Dist: pylint; extra == "dev"
Requires-Dist: pydantic; extra == "dev"
Requires-Dist: mypy; extra == "dev"
Requires-Dist: ruff; extra == "dev"
Requires-Dist: coverage; extra == "dev"
Requires-Dist: pytest-cov; extra == "dev"
Requires-Dist: python-dotenv; extra == "dev"
Dynamic: license-file
